odoo/addons/account_move_sent_usability/README.rst
odoo/addons/account_move_sent_usability/__init__.py
odoo/addons/account_move_sent_usability/__manifest__.py
odoo/addons/account_move_sent_usability/i18n/account_move_sent_usability.pot
odoo/addons/account_move_sent_usability/i18n/it.po
odoo/addons/account_move_sent_usability/readme/CONTRIBUTORS.rst
odoo/addons/account_move_sent_usability/readme/DESCRIPTION.rst
odoo/addons/account_move_sent_usability/static/description/icon.png
odoo/addons/account_move_sent_usability/static/description/index.html
odoo/addons/account_move_sent_usability/static/images/sent_filter.png
odoo/addons/account_move_sent_usability/static/images/sent_form.png
odoo/addons/account_move_sent_usability/views/account_move.xml
odoo_addon_account_move_sent_usability-16.0.1.1.0.dist-info/METADATA
odoo_addon_account_move_sent_usability-16.0.1.1.0.dist-info/WHEEL
odoo_addon_account_move_sent_usability-16.0.1.1.0.dist-info/top_level.txt
odoo_addon_account_move_sent_usability-16.0.1.1.0.dist-info/RECORD
